libname/__init__.py
libname/functions.py
net_modules-0.0.1.dist-info/METADATA
net_modules-0.0.1.dist-info/WHEEL
net_modules-0.0.1.dist-info/top_level.txt
net_modules-0.0.1.dist-info/RECORD
