Metadata-Version: 2.1
Name: net-modules
Version: 0.0.1
Summary: upgrade and deploy networks
Home-page: UNKNOWN
Author: Nokia
Author-email: <mail@neuralnine.com>
License: UNKNOWN
Keywords: python
Platform: UNKNOWN
Classifier: Development Status :: 1 - Planning
Classifier: Intended Audience :: Developers
Classifier: Programming Language :: Python :: 3
Classifier: Operating System :: Unix
Classifier: Operating System :: MacOS :: MacOS X
Classifier: Operating System :: Microsoft :: Windows
Requires-Dist: paramiko
Requires-Dist: scp
Requires-Dist: regex
Requires-Dist: ipywidgets
Requires-Dist: ipython
Requires-Dist: tqdm
Requires-Dist: ipyfilechooser
Requires-Dist: openpyxl
